oxutils/__init__.py
oxutils/apps.py
oxutils/audit/__init__.py
oxutils/audit/apps.py
oxutils/audit/export.py
oxutils/audit/masks.py
oxutils/audit/migrations/0001_initial.py
oxutils/audit/migrations/__init__.py
oxutils/audit/models.py
oxutils/audit/settings.py
oxutils/audit/utils.py
oxutils/celery/__init__.py
oxutils/celery/base.py
oxutils/celery/settings.py
oxutils/conf.py
oxutils/constants.py
oxutils/context/__init__.py
oxutils/context/site_name_processor.py
oxutils/currency/__init__.py
oxutils/currency/admin.py
oxutils/currency/apps.py
oxutils/currency/controllers.py
oxutils/currency/enums.py
oxutils/currency/migrations/0001_initial.py
oxutils/currency/migrations/__init__.py
oxutils/currency/models.py
oxutils/currency/schemas.py
oxutils/currency/tests.py
oxutils/currency/utils.py
oxutils/enums/__init__.py
oxutils/enums/audit.py
oxutils/enums/invoices.py
oxutils/exceptions.py
oxutils/functions.py
oxutils/jwt/__init__.py
oxutils/jwt/auth.py
oxutils/jwt/models.py
oxutils/jwt/tokens.py
oxutils/jwt/utils.py
oxutils/locale/fr/LC_MESSAGES/django.po
oxutils/logger/__init__.py
oxutils/logger/receivers.py
oxutils/logger/settings.py
oxutils/mixins/__init__.py
oxutils/mixins/base.py
oxutils/mixins/schemas.py
oxutils/mixins/services.py
oxutils/models/__init__.py
oxutils/models/base.py
oxutils/models/billing.py
oxutils/models/fields.py
oxutils/models/invoice.py
oxutils/oxiliere/__init__.py
oxutils/oxiliere/admin.py
oxutils/oxiliere/apps.py
oxutils/oxiliere/authorization.py
oxutils/oxiliere/cacheops.py
oxutils/oxiliere/caches.py
oxutils/oxiliere/checks.py
oxutils/oxiliere/constants.py
oxutils/oxiliere/context.py
oxutils/oxiliere/controllers.py
oxutils/oxiliere/enums.py
oxutils/oxiliere/exceptions.py
oxutils/oxiliere/management/__init__.py
oxutils/oxiliere/management/commands/__init__.py
oxutils/oxiliere/management/commands/grant_tenant_owners.py
oxutils/oxiliere/management/commands/init_oxiliere_system.py
oxutils/oxiliere/middleware.py
oxutils/oxiliere/migrations/__init__.py
oxutils-0.1.11.dist-info/WHEEL
oxutils-0.1.11.dist-info/METADATA
oxutils-0.1.11.dist-info/RECORD
