Metadata-Version: 2.4
Name: oxutils
Version: 0.1.11
Summary: Production-ready utilities for Django applications in the Oxiliere ecosystem
Keywords: django,utilities,jwt,s3,audit,logging,celery,structlog
Author: Edimedia Mutoke
Author-email: Edimedia Mutoke <eddycondor07@gmail.com>
License-Expression: Apache-2.0
Classifier: Development Status :: 4 - Beta
Classifier: Framework :: Django
Classifier: Framework :: Django :: 5.0
Classifier: Intended Audience :: Developers
Classifier: License :: OSI Approved :: Apache Software License
Classifier: Operating System :: OS Independent
Classifier: Programming Language :: Python :: 3
Classifier: Programming Language :: Python :: 3.12
Classifier: Topic :: Software Development :: Libraries :: Python Modules
Classifier: Topic :: Internet :: WWW/HTTP
Requires-Dist: boto3>=1.41.5
Requires-Dist: celery>=5.5.3
Requires-Dist: cryptography>=46.0.3
Requires-Dist: django-auditlog>=3.3.0
Requires-Dist: django-celery-results>=2.6.0
Requires-Dist: django-extensions>=4.1
Requires-Dist: django-ninja>=1.5.0
Requires-Dist: django-ninja-extra>=0.30.6
Requires-Dist: django-storages[s3]>=1.14.6
Requires-Dist: django-structlog[celery]>=10.0.0
Requires-Dist: jwcrypto>=1.5.6
Requires-Dist: pydantic-settings>=2.12.0
Requires-Dist: pyjwt>=2.10.1
Requires-Dist: requests>=2.32.5
Requires-Dist: bcc-rates>=1.1.0 ; extra == 'all'
Requires-Dist: django-cacheops>=7.2 ; extra == 'all'
Requires-Dist: django-tenants>=3.9.0 ; extra == 'all'
Requires-Dist: django-safedelete>=1.4.1 ; extra == 'all'
Requires-Dist: django-auditlog>=3.4.1 ; extra == 'all'
Requires-Dist: django-ninja-jwt>=5.4.2 ; extra == 'all'
Requires-Dist: weasyprint>=67.0 ; extra == 'all'
Requires-Dist: bcc-rates>=1.1.0 ; extra == 'currency'
Requires-Dist: django-ninja-jwt>=5.4.2 ; extra == 'jwt'
Requires-Dist: django-cacheops>=7.2 ; extra == 'oxiliere'
Requires-Dist: django-tenants>=3.9.0 ; extra == 'oxiliere'
Requires-Dist: django-safedelete>=1.4.1 ; extra == 'oxiliere'
Requires-Dist: django-auditlog>=3.4.1 ; extra == 'oxiliere'
Requires-Dist: weasyprint>=67.0 ; extra == 'pdf'
Requires-Python: >=3.12
Project-URL: Changelog, https://github.com/oxiliere/oxutils/blob/main/CHANGELOG.md
Project-URL: Documentation, https://github.com/oxiliere/oxutils/tree/main/docs
Project-URL: Homepage, https://github.com/oxiliere/oxutils
Project-URL: Issues, https://github.com/oxiliere/oxutils/issues
Project-URL: Repository, https://github.com/oxiliere/oxutils
Provides-Extra: all
Provides-Extra: currency
Provides-Extra: jwt
Provides-Extra: oxiliere
Provides-Extra: pdf
